setup.py
kevjkcavtltiqvo/__init__.py
kevjkcavtltiqvo/cli.py
kevjkcavtltiqvo.egg-info/PKG-INFO
kevjkcavtltiqvo.egg-info/SOURCES.txt
kevjkcavtltiqvo.egg-info/dependency_links.txt
kevjkcavtltiqvo.egg-info/entry_points.txt
kevjkcavtltiqvo.egg-info/top_level.txt